CHANGELOG.txt
LICENSE
LICENSE.txt
MANIFEST.in
README.md
datawrang.py
setup.py
DataWrang.egg-info/PKG-INFO
DataWrang.egg-info/SOURCES.txt
DataWrang.egg-info/dependency_links.txt
DataWrang.egg-info/requires.txt
DataWrang.egg-info/top_level.txt
datawrang/__init__.py